geohey/__init__.py
geohey/common.py
geohey/foliumap.py
geohey/geohey.py
geohey/utils.py
geohey-0.0.7.dist-info/LICENSE
geohey-0.0.7.dist-info/METADATA
geohey-0.0.7.dist-info/WHEEL
geohey-0.0.7.dist-info/entry_points.txt
geohey-0.0.7.dist-info/top_level.txt
geohey-0.0.7.dist-info/RECORD
