Metadata-Version: 2.1
Name: geohey
Version: 0.0.7
Summary: A Python package demo for geospatial analysis
Author-email: Qiusheng Wu <giswqs@gmail.com>
License: MIT License
Project-URL: Homepage, https://github.com/giswqs/geohey
Keywords: geohey
Classifier: Intended Audience :: Developers
Classifier: License :: OSI Approved :: MIT License
Classifier: Natural Language :: English
Classifier: Programming Language :: Python :: 3.8
Classifier: Programming Language :: Python :: 3.9
Classifier: Programming Language :: Python :: 3.10
Classifier: Programming Language :: Python :: 3.11
Classifier: Programming Language :: Python :: 3.12
Requires-Python: >=3.8
License-File: LICENSE
Requires-Dist: folium
Requires-Dist: ipyleaflet
Requires-Dist: localtileserver
Requires-Dist: numpy
Requires-Dist: pandas
Provides-Extra: all
Requires-Dist: geohey[extra] ; extra == 'all'
Provides-Extra: extra
Requires-Dist: pandas ; extra == 'extra'
